odoo/addons/ssi_account_type_active/README.rst
odoo/addons/ssi_account_type_active/__init__.py
odoo/addons/ssi_account_type_active/__manifest__.py
odoo/addons/ssi_account_type_active/models/__init__.py
odoo/addons/ssi_account_type_active/models/account_account_type.py
odoo/addons/ssi_account_type_active/static/description/icon.png
odoo/addons/ssi_account_type_active/views/account_account_type_views.xml
odoo14_addon_ssi_account_type_active-14.0.1.0.2.dev1.dist-info/METADATA
odoo14_addon_ssi_account_type_active-14.0.1.0.2.dev1.dist-info/WHEEL
odoo14_addon_ssi_account_type_active-14.0.1.0.2.dev1.dist-info/top_level.txt
odoo14_addon_ssi_account_type_active-14.0.1.0.2.dev1.dist-info/RECORD
